camproject/__init__.py
camproject/extrinsics.py
camproject/utils.py
camproject-0.42.dist-info/LICENSE
camproject-0.42.dist-info/METADATA
camproject-0.42.dist-info/WHEEL
camproject-0.42.dist-info/entry_points.txt
camproject-0.42.dist-info/top_level.txt
camproject-0.42.dist-info/RECORD
